Metadata-Version: 2.1
Name: zprp-ffmpeg
Version: 0.1.0
Summary: Implementation of the successor to the ffmpeg-python library
Home-page: https://github.com/Madghostek/zprp-ffmpeg
Author: 
Author-email: 
License: MIT
Project-URL: Documentation, https://zprp-ffmpeg.readthedocs.io/
Project-URL: Changelog, https://zprp-ffmpeg.readthedocs.io/en/latest/changelog.html
Project-URL: Issue Tracker, https://github.com/Madghostek/zprp-ffmpeg/issues
Classifier: Development Status :: 5 - Production/Stable
Classifier: Intended Audience :: Developers
Classifier: License :: OSI Approved :: MIT License
Classifier: Operating System :: Unix
Classifier: Operating System :: POSIX
Classifier: Operating System :: Microsoft :: Windows
Classifier: Programming Language :: Python
Classifier: Programming Language :: Python :: 3
Classifier: Programming Language :: Python :: 3 :: Only
Classifier: Programming Language :: Python :: 3.8
Classifier: Programming Language :: Python :: 3.9
Classifier: Programming Language :: Python :: 3.10
Classifier: Programming Language :: Python :: 3.11
Classifier: Programming Language :: Python :: 3.12
Classifier: Programming Language :: Python :: Implementation :: CPython
Classifier: Programming Language :: Python :: Implementation :: PyPy
Classifier: Topic :: Utilities
Requires-Python: >=3.8
License-File: LICENSE
License-File: AUTHORS.rst
